optipoly.py
optipoly-0.0.2.dist-info/LICENSE
optipoly-0.0.2.dist-info/METADATA
optipoly-0.0.2.dist-info/WHEEL
optipoly-0.0.2.dist-info/top_level.txt
optipoly-0.0.2.dist-info/RECORD
