Metadata-Version: 2.1
Name: optipoly
Version: 0.0.2
Summary: An NLP solver for box-constrained optimization of polynomial cost functions
Author-email: Mazen Alamir <mazen.alamir@grenoble-inp.fr>
Project-URL: Homepage, https://github.com/mazenalamir/optipoly
Project-URL: Issues, https://github.com/mazenalamir/optipoly/issues
Keywords: Nonlinear Programming,optimization,derivative free,constrained optimization,multi-variate polynomial
Classifier: Programming Language :: Python :: 3
Classifier: License :: OSI Approved :: MIT License
Classifier: Operating System :: OS Independent
Requires-Python: >=3.8
License-File: LICENSE
